openwa/__init__.py
openwa/async_driver.py
openwa/helper.py
openwa/wapi_js_wrapper.py
openwa/__pycache__/__init__.cpython-36.pyc
openwa/__pycache__/__init__.cpython-37.pyc
openwa/__pycache__/helper.cpython-37.pyc
openwa/__pycache__/wapi_js_wrapper.cpython-37.pyc
openwa/js/.eslintrc.json
openwa/js/.gitignore
openwa/js/pywapi.js
openwa/js/wapi.js
openwa/js/wapi2.js
openwa/objects/__init__.py
openwa/objects/chat.py
openwa/objects/contact.py
openwa/objects/message.py
openwa/objects/number_status.py
openwa/objects/whatsapp_object.py
openwa/objects/__pycache__/__init__.cpython-37.pyc
openwa/objects/__pycache__/chat.cpython-37.pyc
openwa/objects/__pycache__/contact.cpython-37.pyc
openwa/objects/__pycache__/message.cpython-37.pyc
openwa/objects/__pycache__/number_status.cpython-37.pyc
openwa/objects/__pycache__/whatsapp_object.cpython-37.pyc
openwa-1.3.16.dist-info/LICENSE.txt
openwa-1.3.16.dist-info/METADATA
openwa-1.3.16.dist-info/WHEEL
openwa-1.3.16.dist-info/top_level.txt
openwa-1.3.16.dist-info/RECORD
