Metadata-Version: 2.1
Name: openwa
Version: 1.3.16
Summary: A python interface for Whatsapp Web
Home-page: UNKNOWN
Author: Mukul Hase
Author-email: mukulhase@gmail.com
License: MIT
Keywords: Whatsapp Chat Bot Chatbot Selenium Web Whatsapp API
Platform: UNKNOWN
Classifier: Development Status :: 4 - Beta
Classifier: Intended Audience :: Developers
Classifier: Topic :: Communications :: Chat
Classifier: License :: OSI Approved :: MIT License
Classifier: Programming Language :: Python :: 3.8
